webdav/__init__.py
webdav/client.py
webdav/connection.py
webdav/exceptions.py
webdav/urn.py
webdav-1.1.7.dist-info/LICENSE
webdav-1.1.7.dist-info/METADATA
webdav-1.1.7.dist-info/WHEEL
webdav-1.1.7.dist-info/top_level.txt
webdav-1.1.7.dist-info/RECORD
